{
  "name": "AmbulanceActivity",
  "fields": [
    {
      "fieldName": "ambulanceNumber",
      "fieldType": "String"
    },
    {
      "fieldName": "ambulanceType",
      "fieldType": "String"
    },
    {
      "fieldName": "driverName",
      "fieldType": "String"
    },
    {
      "fieldName": "driverPrimaryTelephoneNo",
      "fieldType": "String"
    },
    {
      "fieldName": "driverSecondaryTelephoneNo",
      "fieldType": "String"
    },
    {
      "fieldName": "profession",
      "fieldType": "String"
    },
    {
      "fieldName": "originAddress",
      "fieldType": "String"
    },
    {
      "fieldName": "destinationAddress",
      "fieldType": "String"
    },
    {
      "fieldName": "pickupDateTime",
      "fieldType": "Instant"
    },
    {
      "fieldName": "dropDateTime",
      "fieldType": "Instant"
    },
    {
      "fieldName": "facilityProviderIdRef",
      "fieldType": "Long"
    },
    {
      "fieldName": "ambulanceServiceIdRef",
      "fieldType": "Long"
    },
    {
      "fieldName": "patientActivityIdRef",
      "fieldType": "Long"
    },
    {
      "fieldName": "personActivityIdRef",
      "fieldType": "Long"
    }
  ],
  "relationships": [],
  "changelogDate": "20200826151603",
  "entityTableName": "ambulance_activity",
  "dto": "mapstruct",
  "pagination": "pagination",
  "service": "serviceImpl",
  "jpaMetamodelFiltering": false,
  "fluentMethods": true,
  "readOnly": false,
  "embedded": false,
  "clientRootFolder": "ambulanceactivityservice",
  "applications": "*",
  "microserviceName": "ambulanceactivityservice",
  "enableEntityAudit": true
}
